kbengine_tips/Math.py
kbengine_tips/Types.py
kbengine_tips/__init__.py
kbengine_tips/common.py
kbengine_tips/BaseApp/KBEngine.py
kbengine_tips/BaseApp/__init__.py
kbengine_tips/Bots/KBEngine.py
kbengine_tips/Bots/__init__.py
kbengine_tips/CellApp/KBEngine.py
kbengine_tips/CellApp/__init__.py
kbengine_tips/ClientPlugins/KBEngine.py
kbengine_tips/ClientPlugins/__init__.py
kbengine_tips/DBMgr/KBEngine.py
kbengine_tips/DBMgr/__init__.py
kbengine_tips/Interface/KBEngine.py
kbengine_tips/Interface/__init__.py
kbengine_tips/Logger/KBEngine.py
kbengine_tips/Logger/__init__.py
kbengine_tips/LoginApp/KBEngine.py
kbengine_tips/LoginApp/__init__.py
kbengine_tips-1.2.0.dist-info/LICENSE
kbengine_tips-1.2.0.dist-info/METADATA
kbengine_tips-1.2.0.dist-info/WHEEL
kbengine_tips-1.2.0.dist-info/top_level.txt
kbengine_tips-1.2.0.dist-info/RECORD
