Metadata-Version: 2.1
Name: kbengine-tips
Version: 1.2.0
Summary: KBEngine编码提示
Home-page: https://github.com/jackylvm/kbengine_tips
Author: jacky
Author-email: jackylvm@foxmail.com
License: GPL 3.0
Platform: UNKNOWN
License-File: LICENSE
